py_image_border/__init__.py
py_image_border/add_border.py
py_image_border/cli.py
py_image_border/image_processing.py
py_image_border-2023.4.14.2.dist-info/entry_points.txt
py_image_border-2023.4.14.2.dist-info/WHEEL
py_image_border-2023.4.14.2.dist-info/METADATA
py_image_border-2023.4.14.2.dist-info/RECORD
