Metadata-Version: 2.1
Name: py-image-border
Version: 2023.4.14.2
Summary: Add a border to any image.
Author: Eric Matthes
Requires-Python: >=3.8
Classifier: Programming Language :: Python :: 3
Classifier: License :: OSI Approved :: MIT License
Classifier: Operating System :: OS Independent
Requires-Dist: Pillow
Project-URL: Homepage, https://github.com/ehmatthes/py-image-border
Project-URL: Issues, https://github.com/ehmatthes/py-image-border/issues
